trio_mysql/__init__.py
trio_mysql/_auth.py
trio_mysql/_compat.py
trio_mysql/_version.py
trio_mysql/charset.py
trio_mysql/connections.py
trio_mysql/converters.py
trio_mysql/cursors.py
trio_mysql/err.py
trio_mysql/optionfile.py
trio_mysql/protocol.py
trio_mysql/times.py
trio_mysql/constants/CLIENT.py
trio_mysql/constants/COMMAND.py
trio_mysql/constants/CR.py
trio_mysql/constants/ER.py
trio_mysql/constants/FIELD_TYPE.py
trio_mysql/constants/FLAG.py
trio_mysql/constants/SERVER_STATUS.py
trio_mysql/constants/__init__.py
trio_mysql-1.0.3.dist-info/LICENSE
trio_mysql-1.0.3.dist-info/METADATA
trio_mysql-1.0.3.dist-info/WHEEL
trio_mysql-1.0.3.dist-info/top_level.txt
trio_mysql-1.0.3.dist-info/RECORD
