Metadata-Version: 2.1
Name: trio-mysql
Version: 1.0.3
Summary: Pure Python MySQL Driver
Home-page: https://github.com/python-trio/trio-mysql/
Author: Matthias Urlichs
Author-email: matthias@urlichs.de
Maintainer: Inada Naoki
Maintainer-email: songofacandy@gmail.com
License: MIT
Project-URL: Documentation, https://trio_mysql.readthedocs.io/
Keywords: MySQL
Platform: UNKNOWN
Classifier: Development Status :: 5 - Production/Stable
Classifier: Programming Language :: Python :: 3
Classifier: Programming Language :: Python :: 3.6
Classifier: Programming Language :: Python :: 3.7
Classifier: Programming Language :: Python :: 3.8
Classifier: Programming Language :: Python :: 3.9
Classifier: Programming Language :: Python :: Implementation :: CPython
Classifier: Programming Language :: Python :: Implementation :: PyPy
Classifier: Intended Audience :: Developers
Classifier: License :: OSI Approved :: MIT License
Classifier: Topic :: Database
Classifier: Framework :: Trio
Requires-Python: >=3.6
License-File: LICENSE
Requires-Dist: trio (>=0.18)
Provides-Extra: ed25519
Requires-Dist: PyNaCl (>=1.4.0) ; extra == 'ed25519'
Provides-Extra: rsa
Requires-Dist: cryptography ; extra == 'rsa'
